readyml/__init__.py
readyml/facegeneration.py
readyml/imageclassification.py
readyml/imagegeneration.py
readyml/objectdetection.py
readyml/labels/labels_loader.py
readyml/utils/visualization_utils.py
readyml-0.0.2.dist-info/LICENSE
readyml-0.0.2.dist-info/METADATA
readyml-0.0.2.dist-info/WHEEL
readyml-0.0.2.dist-info/top_level.txt
readyml-0.0.2.dist-info/RECORD
