Metadata-Version: 2.1
Name: readyml
Version: 0.0.2
Summary: ReadyML - Easy and Ready Machine Learning.
Home-page: https://github.com/houseofai/readyml
Author: Odyssée
License: LICENSE
Platform: UNKNOWN
Requires-Python: >=3.8.0
Requires-Dist: tensorflow-hub (==0.12.0)
Requires-Dist: tensorflow (==2.5.0)
Requires-Dist: pillow
